{"resumo":{"alvo":{"nivel":"ESC","chave":"23244747","rede":"T","nome":"EEEP JAIME ALENCAR DE OLIVEIRA","uf":"CE","n_participantes":172,"n_cn":169,"media_cn":508.8,"n_ch":170,"media_ch":529.7,"n_lc":170,"media_lc":548.5,"n_mt":169,"media_mt":567.4,"n_red":170,"media_red":623.4,"media_comp1":116.0,"media_comp2":136.7,"media_comp3":117.9,"media_comp4":129.5,"media_comp5":123.3,"media_geral":555.7,"escola":{"chave":"23244747","co_municipio":"2304400","municipio":"Fortaleza","uf":"CE","dependencia":2,"localizacao":1,"n_participantes":172,"nome":"EEEP JAIME ALENCAR DE OLIVEIRA","dependencia_nome":"Estadual"}},"contexto_por_rede":{"T":[{"nivel":"MUN","chave":"2304400","rede":"T","nome":"Fortaleza","uf":"CE","n_participantes":30036,"n_cn":24678,"media_cn":494.6,"n_ch":25389,"media_ch":504.7,"n_lc":25389,"media_lc":526.1,"n_mt":24678,"media_mt":516.0,"n_red":25389,"media_red":581.1,"media_comp1":110.7,"media_comp2":128.5,"media_comp3":110.7,"media_comp4":119.6,"media_comp5":111.7,"media_geral":526.8},{"nivel":"UF","chave":"CE","rede":"T","nome":"CE","uf":"CE","n_participantes":115344,"n_cn":97062,"media_cn":476.2,"n_ch":99388,"media_ch":483.9,"n_lc":99388,"media_lc":505.1,"n_mt":97062,"media_mt":490.3,"n_red":99388,"media_red":531.7,"media_comp1":102.1,"media_comp2":116.8,"media_comp3":102.2,"media_comp4":110.5,"media_comp5":100.2,"media_geral":499.4},{"nivel":"BR","chave":"BR","rede":"T","nome":"Brasil","uf":null,"n_participantes":1739028,"n_cn":1292603,"media_cn":491.6,"n_ch":1352562,"media_ch":502.9,"n_lc":1352562,"media_lc":524.5,"n_mt":1292603,"media_mt":513.8,"n_red":1352562,"media_red":573.2,"media_comp1":111.0,"media_comp2":127.1,"media_comp3":110.5,"media_comp4":118.2,"media_comp5":106.4,"media_geral":524.1}],"PUB":[{"nivel":"MUN","chave":"2304400","rede":"PUB","nome":"Fortaleza","uf":"CE","n_participantes":24272,"n_cn":19246,"media_cn":475.2,"n_ch":19880,"media_ch":485.8,"n_lc":19880,"media_lc":511.7,"n_mt":19246,"media_mt":483.3,"n_red":19880,"media_red":533.3,"media_comp1":103.1,"media_comp2":120.0,"media_comp3":102.2,"media_comp4":109.2,"media_comp5":98.7,"media_geral":500.2},{"nivel":"UF","chave":"CE","rede":"PUB","nome":"CE","uf":"CE","n_participantes":106723,"n_cn":88915,"media_cn":468.7,"n_ch":91134,"media_ch":476.3,"n_lc":91134,"media_lc":498.8,"n_mt":88915,"media_mt":478.1,"n_red":91134,"media_red":511.5,"media_comp1":98.8,"media_comp2":113.1,"media_comp3":98.6,"media_comp4":106.2,"media_comp5":94.8,"media_geral":488.6},{"nivel":"BR","chave":"BR","rede":"PUB","nome":"Brasil","uf":null,"n_participantes":1466229,"n_cn":1040122,"media_cn":476.9,"n_ch":1095297,"media_ch":488.0,"n_lc":1095297,"media_lc":512.0,"n_mt":1040122,"media_mt":488.0,"n_red":1095297,"media_red":536.5,"media_comp1":105.3,"media_comp2":120.5,"media_comp3":104.2,"media_comp4":110.6,"media_comp5":95.9,"media_geral":503.1}],"PRIV":[{"nivel":"MUN","chave":"2304400","rede":"PRIV","nome":"Fortaleza","uf":"CE","n_participantes":5764,"n_cn":5432,"media_cn":563.3,"n_ch":5509,"media_ch":572.7,"n_lc":5509,"media_lc":578.0,"n_mt":5432,"media_mt":632.0,"n_red":5509,"media_red":754.0,"media_comp1":138.1,"media_comp2":159.1,"media_comp3":141.2,"media_comp4":156.9,"media_comp5":158.6,"media_geral":621.1},{"nivel":"UF","chave":"CE","rede":"PRIV","nome":"CE","uf":"CE","n_participantes":8621,"n_cn":8147,"media_cn":558.0,"n_ch":8254,"media_ch":567.8,"n_lc":8254,"media_lc":574.1,"n_mt":8147,"media_mt":623.6,"n_red":8254,"media_red":754.5,"media_comp1":138.1,"media_comp2":158.6,"media_comp3":141.3,"media_comp4":157.1,"media_comp5":159.3,"media_geral":616.6},{"nivel":"BR","chave":"BR","rede":"PRIV","nome":"Brasil","uf":null,"n_participantes":272799,"n_cn":252481,"media_cn":551.9,"n_ch":257265,"media_ch":566.2,"n_lc":257265,"media_lc":577.6,"n_mt":252481,"media_mt":620.3,"n_red":257265,"media_red":729.7,"media_comp1":135.5,"media_comp2":155.1,"media_comp3":137.5,"media_comp4":150.8,"media_comp5":150.8,"media_geral":610.5}]}},"itens":{"CH":[[111883,170,0.159,0.25,12,2.18,null],[140491,170,0.171,0.171,26,1.38,null],[141162,170,0.182,0.176,12,2.19,null],[95495,170,0.194,0.183,11,1.65,null],[141340,170,0.212,0.149,24,2.72,null],[141167,170,0.224,0.205,22,1.57,null],[84849,170,0.224,0.271,10,2.68,null],[125788,170,0.265,0.23,21,1.59,null],[140432,170,0.271,0.311,7,2.65,null],[140201,170,0.282,0.278,23,1.52,null],[87509,170,0.294,0.269,2,1.15,null],[111982,170,0.318,0.245,21,1.3,null],[84812,170,0.318,0.254,1,1.23,null],[149742,170,0.318,0.371,4,1.01,null],[85827,170,0.335,0.162,13,2.09,null],[88661,170,0.335,0.316,1,1.37,null],[140932,170,0.341,0.294,25,1.41,null],[111941,170,0.347,0.35,25,1.02,null],[125735,170,0.371,0.371,29,0.98,null],[141078,170,0.382,0.403,17,0.87,null],[56054,170,0.382,0.404,11,0.9,null],[56368,170,0.4,0.184,27,1.75,null],[95807,170,0.4,0.316,16,1.19,null],[55581,170,0.406,0.469,23,0.46,null],[118057,170,0.412,0.409,30,0.77,null],[149824,170,0.412,0.52,6,0.61,null],[141102,170,0.441,0.353,7,1.0,null],[141135,170,0.471,0.453,22,0.51,null],[140451,170,0.482,0.514,14,0.41,null],[140594,170,0.5,0.401,19,1.15,null],[55300,170,0.512,0.432,9,0.62,null],[149787,170,0.512,0.402,4,0.67,null],[112144,170,0.518,0.419,18,0.94,null],[140518,170,0.529,0.571,28,0.42,null],[141009,170,0.535,0.563,23,0.17,null],[140428,170,0.547,0.607,8,0.38,null],[90024,170,0.553,0.461,19,0.8,null],[85913,170,0.553,0.552,3,0.5,null],[140583,170,0.594,0.639,26,0.33,null],[96978,170,0.594,0.656,15,0.39,null],[83900,170,0.606,0.64,5,0.32,null],[111927,170,0.618,0.548,20,0.48,null],[85670,170,0.618,0.598,24,0.02,null],[149784,170,0.635,0.6,27,0.44,null],[118062,170,0.641,0.64,28,0.36,null]],"LC":[[140908,170,0.1,0.094,29,1.5,null],[154015,75,0.133,0.132,8,1.66,1],[157775,170,0.147,0.271,22,1.08,null],[153420,170,0.247,0.176,20,1.72,null],[153945,75,0.253,0.259,8,1.32,1],[150607,170,0.276,0.294,16,1.53,null],[157781,170,0.276,0.295,30,1.04,null],[157598,170,0.312,0.27,18,1.95,null],[157779,170,0.324,0.271,29,1.24,null],[150761,170,0.329,0.312,17,1.07,null],[150940,170,0.347,0.371,15,0.92,null],[153681,170,0.359,0.36,26,1.01,null],[158716,170,0.365,0.304,14,1.01,null],[43532,170,0.382,0.344,18,0.98,null],[150642,170,0.394,0.422,23,1.31,null],[66526,170,0.412,0.479,25,0.73,null],[150643,170,0.412,0.442,24,0.86,null],[153400,170,0.447,0.394,27,0.81,null],[157615,170,0.447,0.427,15,0.96,null],[120341,170,0.459,0.362,19,0.96,null],[153392,170,0.465,0.454,17,0.8,null],[153550,170,0.465,0.451,12,0.98,null],[97881,170,0.488,0.47,22,0.9,null],[157750,170,0.506,0.446,1,0.9,null],[153556,170,0.518,0.515,13,0.74,null],[150612,170,0.524,0.562,20,0.62,null],[150505,170,0.524,0.544,16,0.54,null],[157593,170,0.547,0.446,3,0.66,null],[153833,75,0.573,0.517,5,0.44,1],[140709,75,0.587,0.311,7,0.94,1],[157751,170,0.588,0.59,4,0.49,null],[152784,170,0.588,0.688,30,0.37,null],[157665,170,0.588,0.573,21,0.32,null],[153836,95,0.611,0.629,6,0.68,0],[17166,170,0.624,0.575,24,0.66,null],[150674,170,0.629,0.565,2,0.63,null],[153419,170,0.629,0.602,28,0.11,null],[152688,75,0.653,0.563,6,0.37,1],[120714,170,0.676,0.609,4,0.6,null],[158757,170,0.676,0.711,12,0.28,null],[140845,170,0.694,0.718,2,0.21,null],[157571,170,0.694,0.749,11,0.19,null],[112036,95,0.695,0.622,5,0.71,0],[154020,170,0.765,0.827,9,-0.03,null],[153875,95,0.789,0.814,7,0.37,0],[118169,95,0.789,0.707,7,0.6,0],[118196,170,0.812,0.806,9,-0.04,null],[157619,170,0.824,0.87,10,-0.3,null],[153930,95,0.842,0.85,6,0.19,0],[44047,170,0.894,0.929,26,-0.6,null]],"CN":[[60058,169,0.041,0.076,3,2.0,null],[96328,169,0.124,0.076,26,1.93,null],[97292,169,0.142,0.129,1,1.63,null],[141529,169,0.16,0.271,5,1.8,null],[86958,169,0.16,0.158,17,2.09,null],[85481,169,0.166,0.201,19,1.27,null],[84440,169,0.166,0.138,9,1.41,null],[67752,169,0.183,0.122,20,1.91,null],[87716,169,0.183,0.244,22,1.04,null],[141577,169,0.207,0.224,23,1.1,null],[77992,169,0.207,0.103,7,2.22,null],[141609,169,0.219,0.159,5,1.47,null],[61018,169,0.225,0.181,20,1.63,null],[83213,169,0.231,0.194,21,1.92,null],[95445,169,0.237,0.239,8,1.12,null],[97091,169,0.26,0.192,24,2.18,null],[89916,169,0.296,0.237,28,1.04,null],[141642,169,0.296,0.288,6,2.44,null],[141522,169,0.302,0.298,2,2.88,null],[76686,169,0.302,0.218,18,1.76,null],[117652,169,0.302,0.262,7,0.81,null],[111737,169,0.314,0.322,27,1.01,null],[141671,169,0.325,0.289,12,1.25,null],[117734,169,0.349,0.169,28,1.25,null],[86643,169,0.355,0.341,3,1.04,null],[111667,169,0.361,0.207,14,1.54,null],[141601,169,0.373,0.332,23,1.65,null],[83614,168,0.375,0.264,24,1.14,null],[141754,169,0.432,0.406,11,0.62,null],[141590,169,0.444,0.395,1,0.6,null],[98246,169,0.456,0.398,15,0.64,null],[76022,169,0.503,0.493,21,0.81,null],[88062,169,0.515,0.448,29,0.53,null],[97616,169,0.515,0.43,17,0.52,null],[78625,169,0.521,0.482,22,0.99,null],[87450,169,0.544,0.412,13,0.63,null],[88181,169,0.574,0.562,30,-0.14,null],[97650,169,0.586,0.693,25,-0.22,null],[141710,169,0.609,0.605,4,0.33,null],[44307,169,0.657,0.588,28,-0.02,null],[117869,169,0.692,0.606,16,0.06,null],[97320,169,0.728,0.696,10,-0.11,null]],"MT":[[141568,169,0.059,0.095,18,2.92,null],[141562,169,0.089,0.148,9,2.57,null],[111771,169,0.124,0.19,15,2.19,null],[8460,169,0.13,0.113,29,2.81,null],[95816,169,0.136,0.131,19,4.24,null],[96778,169,0.16,0.207,28,1.9,null],[88952,169,0.166,0.209,22,2.43,null],[27847,169,0.178,0.099,3,3.46,null],[84405,169,0.183,0.201,2,2.27,null],[49136,169,0.189,0.179,7,2.98,null],[16540,169,0.201,0.295,8,2.35,null],[63713,169,0.213,0.257,30,1.73,null],[16995,169,0.231,0.239,28,2.23,null],[49227,169,0.237,0.376,29,1.96,null],[15396,169,0.26,0.334,11,1.39,null],[44306,169,0.26,0.35,25,1.72,null],[111422,169,0.266,0.259,13,2.17,null],[84096,169,0.272,0.247,2,2.29,null],[125905,168,0.28,0.315,6,1.78,null],[117856,169,0.314,0.352,18,1.83,null],[83575,169,0.314,0.233,23,2.46,null],[44510,169,0.355,0.344,12,2.37,null],[141518,169,0.367,0.438,6,1.27,null],[111673,169,0.373,0.366,14,2.02,null],[117625,169,0.391,0.504,19,1.24,null],[86942,169,0.391,0.355,9,2.91,null],[28216,168,0.393,0.355,8,1.83,null],[63293,169,0.426,0.367,5,1.92,null],[125926,169,0.462,0.466,11,1.07,null],[41895,169,0.467,0.48,12,1.39,null],[31953,169,0.491,0.442,16,1.53,null],[126023,169,0.491,0.65,10,0.46,null],[50210,169,0.509,0.472,24,0.97,null],[83162,169,0.521,0.469,26,1.18,null],[28587,169,0.521,0.49,16,1.06,null],[60344,169,0.521,0.517,4,0.88,null],[95625,169,0.544,0.561,17,0.77,null],[63313,169,0.615,0.617,4,0.32,null],[153134,169,0.639,0.57,3,0.85,null],[38222,169,0.663,0.529,27,0.99,null],[96979,169,0.751,0.734,1,0.09,null],[117764,169,0.781,0.796,20,-0.19,null],[96852,169,0.828,0.706,25,0.32,null]]},"hist_resumo":[{"ano":2024,"n_participantes":163,"media_geral":570.0,"media_cn":502.4,"media_ch":522.0,"media_lc":536.0,"media_mt":552.6,"media_red":736.1,"media_comp1":134.3,"media_comp2":164.6,"media_comp3":136.9,"media_comp4":149.4,"media_comp5":151.0},{"ano":2025,"n_participantes":172,"media_geral":555.7,"media_cn":508.8,"media_ch":529.7,"media_lc":548.5,"media_mt":567.4,"media_red":623.4,"media_comp1":116.0,"media_comp2":136.7,"media_comp3":117.9,"media_comp4":129.5,"media_comp5":123.3}],"hist_scope":{"primeiro_ano_com_escola":2024,"nota":"Antes de 2024 o INEP não expunha o código INEP nos microdados; portanto o histórico da escola começa em 2024."}}