{"resumo":{"alvo":{"nivel":"ESC","chave":"50018027","rede":"T","nome":"Escola INEP 50018027","uf":"MS","n_participantes":79,"n_cn":68,"media_cn":472.5,"n_ch":72,"media_ch":477.9,"n_lc":72,"media_lc":507.1,"n_mt":68,"media_mt":468.5,"n_red":72,"media_red":467.8,"media_comp1":95.0,"media_comp2":111.9,"media_comp3":90.6,"media_comp4":96.7,"media_comp5":73.6,"media_geral":483.5,"escola":{"chave":"50018027","co_municipio":"5005400","municipio":"Maracaju","uf":"MS","dependencia":2,"localizacao":1,"n_participantes":79,"nome":null,"dependencia_nome":"Estadual"}},"contexto_por_rede":{"T":[{"nivel":"MUN","chave":"5005400","rede":"T","nome":"Maracaju","uf":"MS","n_participantes":214,"n_cn":180,"media_cn":487.2,"n_ch":192,"media_ch":499.4,"n_lc":192,"media_lc":524.9,"n_mt":180,"media_mt":498.1,"n_red":192,"media_red":542.8,"media_comp1":106.5,"media_comp2":124.3,"media_comp3":104.9,"media_comp4":110.3,"media_comp5":96.9,"media_geral":515.1},{"nivel":"UF","chave":"MS","rede":"T","nome":"MS","uf":"MS","n_participantes":21553,"n_cn":16435,"media_cn":492.9,"n_ch":17370,"media_ch":503.2,"n_lc":17370,"media_lc":523.9,"n_mt":16435,"media_mt":507.3,"n_red":17370,"media_red":563.0,"media_comp1":110.3,"media_comp2":126.4,"media_comp3":109.2,"media_comp4":115.9,"media_comp5":101.3,"media_geral":521.5},{"nivel":"BR","chave":"BR","rede":"T","nome":"Brasil","uf":null,"n_participantes":1739028,"n_cn":1292603,"media_cn":491.6,"n_ch":1352562,"media_ch":502.9,"n_lc":1352562,"media_lc":524.5,"n_mt":1292603,"media_mt":513.8,"n_red":1352562,"media_red":573.2,"media_comp1":111.0,"media_comp2":127.1,"media_comp3":110.5,"media_comp4":118.2,"media_comp5":106.4,"media_geral":524.1}],"PUB":[{"nivel":"MUN","chave":"5005400","rede":"PUB","nome":"Maracaju","uf":"MS","n_participantes":169,"n_cn":139,"media_cn":477.1,"n_ch":150,"media_ch":488.2,"n_lc":150,"media_lc":513.2,"n_mt":139,"media_mt":473.4,"n_red":150,"media_red":504.7,"media_comp1":99.9,"media_comp2":118.1,"media_comp3":98.7,"media_comp4":102.7,"media_comp5":85.3,"media_geral":496.0},{"nivel":"UF","chave":"MS","rede":"PUB","nome":"MS","uf":"MS","n_participantes":18688,"n_cn":13804,"media_cn":480.5,"n_ch":14697,"media_ch":492.3,"n_lc":14697,"media_lc":514.8,"n_mt":13804,"media_mt":486.1,"n_red":14697,"media_red":533.9,"media_comp1":105.8,"media_comp2":121.4,"media_comp3":104.2,"media_comp4":109.8,"media_comp5":92.8,"media_geral":504.8},{"nivel":"BR","chave":"BR","rede":"PUB","nome":"Brasil","uf":null,"n_participantes":1466229,"n_cn":1040122,"media_cn":476.9,"n_ch":1095297,"media_ch":488.0,"n_lc":1095297,"media_lc":512.0,"n_mt":1040122,"media_mt":488.0,"n_red":1095297,"media_red":536.5,"media_comp1":105.3,"media_comp2":120.5,"media_comp3":104.2,"media_comp4":110.6,"media_comp5":95.9,"media_geral":503.1}],"PRIV":[{"nivel":"MUN","chave":"5005400","rede":"PRIV","nome":"Maracaju","uf":"MS","n_participantes":45,"n_cn":41,"media_cn":521.5,"n_ch":42,"media_ch":539.4,"n_lc":42,"media_lc":566.8,"n_mt":41,"media_mt":581.6,"n_red":42,"media_red":679.0,"media_comp1":130.0,"media_comp2":146.2,"media_comp3":127.1,"media_comp4":137.6,"media_comp5":138.1,"media_geral":580.1},{"nivel":"UF","chave":"MS","rede":"PRIV","nome":"MS","uf":"MS","n_participantes":2865,"n_cn":2631,"media_cn":557.6,"n_ch":2673,"media_ch":563.3,"n_lc":2673,"media_lc":574.1,"n_mt":2631,"media_mt":618.0,"n_red":2673,"media_red":723.2,"media_comp1":135.2,"media_comp2":153.7,"media_comp3":137.1,"media_comp4":149.3,"media_comp5":147.9,"media_geral":608.9},{"nivel":"BR","chave":"BR","rede":"PRIV","nome":"Brasil","uf":null,"n_participantes":272799,"n_cn":252481,"media_cn":551.9,"n_ch":257265,"media_ch":566.2,"n_lc":257265,"media_lc":577.6,"n_mt":252481,"media_mt":620.3,"n_red":257265,"media_red":729.7,"media_comp1":135.5,"media_comp2":155.1,"media_comp3":137.5,"media_comp4":150.8,"media_comp5":150.8,"media_geral":610.5}]}},"itens":{"LC":[[140908,72,0.056,0.066,29,1.5,null],[157781,72,0.097,0.175,30,1.04,null],[43532,72,0.153,0.218,18,0.98,null],[154015,31,0.161,0.13,8,1.66,1],[112036,41,0.171,0.28,5,0.71,0],[153420,72,0.181,0.153,20,1.72,null],[157775,72,0.181,0.167,22,1.08,null],[158716,72,0.181,0.164,14,1.01,null],[153400,72,0.194,0.181,27,0.81,null],[153945,31,0.226,0.235,8,1.32,1],[157598,72,0.264,0.248,18,1.95,null],[157750,72,0.264,0.303,1,0.9,null],[120341,72,0.278,0.219,19,0.96,null],[153681,72,0.292,0.243,26,1.01,null],[150940,72,0.306,0.232,15,0.92,null],[157779,72,0.306,0.176,29,1.24,null],[150761,72,0.306,0.191,17,1.07,null],[157751,72,0.319,0.329,4,0.49,null],[153556,72,0.333,0.346,13,0.74,null],[17166,72,0.333,0.373,24,0.66,null],[153550,72,0.333,0.332,12,0.98,null],[153836,41,0.341,0.342,6,0.68,0],[153392,72,0.361,0.279,17,0.8,null],[150607,72,0.361,0.242,16,1.53,null],[157593,72,0.361,0.28,3,0.66,null],[153875,41,0.366,0.442,7,0.37,0],[66526,72,0.389,0.276,25,0.73,null],[150612,72,0.389,0.366,20,0.62,null],[157615,72,0.389,0.297,15,0.96,null],[150674,72,0.389,0.38,2,0.63,null],[157665,72,0.403,0.414,21,0.32,null],[118169,41,0.415,0.403,7,0.6,0],[140709,31,0.419,0.259,7,0.94,1],[97881,72,0.458,0.333,22,0.9,null],[153930,41,0.463,0.567,6,0.19,0],[150505,72,0.5,0.383,16,0.54,null],[150643,72,0.5,0.283,24,0.86,null],[158757,72,0.528,0.465,12,0.28,null],[120714,72,0.528,0.412,4,0.6,null],[153833,31,0.548,0.421,5,0.44,1],[152784,72,0.556,0.45,30,0.37,null],[153419,72,0.569,0.494,28,0.11,null],[118196,72,0.569,0.613,9,-0.04,null],[157571,72,0.611,0.545,11,0.19,null],[150642,72,0.639,0.348,23,1.31,null],[152688,31,0.645,0.505,6,0.37,1],[140845,72,0.653,0.506,2,0.21,null],[154020,72,0.708,0.655,9,-0.03,null],[157619,72,0.75,0.754,10,-0.3,null],[44047,72,0.875,0.861,26,-0.6,null]],"CH":[[141162,72,0.069,0.163,12,2.19,null],[56368,72,0.069,0.138,27,1.75,null],[140491,72,0.083,0.107,26,1.38,null],[111982,72,0.111,0.157,21,1.3,null],[85827,72,0.139,0.139,13,2.09,null],[141167,72,0.139,0.158,22,1.57,null],[84812,72,0.153,0.158,1,1.23,null],[95495,72,0.153,0.155,11,1.65,null],[56054,72,0.167,0.246,11,0.9,null],[87509,72,0.167,0.165,2,1.15,null],[149742,72,0.181,0.236,4,1.01,null],[55300,72,0.181,0.25,9,0.62,null],[112144,72,0.194,0.28,18,0.94,null],[141340,72,0.222,0.146,24,2.72,null],[140932,72,0.264,0.227,25,1.41,null],[141102,72,0.264,0.213,7,1.0,null],[125788,72,0.264,0.165,21,1.59,null],[88661,72,0.264,0.228,1,1.37,null],[111883,72,0.264,0.249,12,2.18,null],[118057,72,0.264,0.211,30,0.77,null],[149824,72,0.278,0.299,6,0.61,null],[141078,72,0.278,0.235,17,0.87,null],[125735,72,0.278,0.229,29,0.98,null],[95807,72,0.292,0.221,16,1.19,null],[149787,72,0.292,0.205,4,0.67,null],[84849,72,0.306,0.271,10,2.68,null],[111927,72,0.319,0.313,20,0.48,null],[140432,72,0.333,0.311,7,2.65,null],[140201,72,0.347,0.229,23,1.52,null],[111941,72,0.347,0.215,25,1.02,null],[141135,72,0.361,0.303,22,0.51,null],[55581,72,0.375,0.276,23,0.46,null],[90024,72,0.389,0.287,19,0.8,null],[140518,72,0.403,0.347,28,0.42,null],[140451,72,0.417,0.311,14,0.41,null],[140428,72,0.417,0.375,8,0.38,null],[85913,72,0.444,0.337,3,0.5,null],[140594,72,0.444,0.301,19,1.15,null],[83900,72,0.486,0.417,5,0.32,null],[149784,72,0.486,0.364,27,0.44,null],[118062,72,0.514,0.446,28,0.36,null],[96978,72,0.514,0.443,15,0.39,null],[141009,72,0.625,0.404,23,0.17,null],[85670,72,0.639,0.444,24,0.02,null],[140583,72,0.667,0.481,26,0.33,null]],"CN":[[85481,68,0.059,0.166,19,1.27,null],[60058,68,0.118,0.068,3,2.0,null],[117734,68,0.118,0.115,28,1.25,null],[141529,68,0.132,0.263,5,1.8,null],[96328,68,0.147,0.069,26,1.93,null],[77992,68,0.147,0.099,7,2.22,null],[67752,68,0.147,0.114,20,1.91,null],[111667,68,0.162,0.152,14,1.54,null],[97292,68,0.162,0.114,1,1.63,null],[86958,68,0.176,0.146,17,2.09,null],[141609,68,0.176,0.126,5,1.47,null],[95445,68,0.176,0.196,8,1.12,null],[97091,68,0.191,0.184,24,2.18,null],[61018,68,0.206,0.163,20,1.63,null],[76686,68,0.206,0.203,18,1.76,null],[89916,68,0.206,0.167,28,1.04,null],[141577,68,0.235,0.16,23,1.1,null],[117652,68,0.235,0.151,7,0.81,null],[84440,68,0.235,0.111,9,1.41,null],[141754,68,0.235,0.278,11,0.62,null],[141601,68,0.235,0.317,23,1.65,null],[83614,68,0.265,0.19,24,1.14,null],[83213,68,0.279,0.187,21,1.92,null],[87716,68,0.279,0.18,22,1.04,null],[111737,68,0.294,0.25,27,1.01,null],[141671,68,0.294,0.258,12,1.25,null],[97616,68,0.309,0.289,17,0.52,null],[141522,68,0.309,0.295,2,2.88,null],[97650,68,0.324,0.589,25,-0.22,null],[86643,68,0.338,0.278,3,1.04,null],[87450,68,0.353,0.295,13,0.63,null],[141590,68,0.382,0.269,1,0.6,null],[88062,68,0.382,0.309,29,0.53,null],[76022,68,0.397,0.418,21,0.81,null],[141642,68,0.412,0.286,6,2.44,null],[98246,68,0.412,0.29,15,0.64,null],[44307,68,0.485,0.452,28,-0.02,null],[78625,68,0.529,0.421,22,0.99,null],[88181,68,0.544,0.471,30,-0.14,null],[117869,68,0.632,0.476,16,0.06,null],[141710,68,0.647,0.479,4,0.33,null],[97320,68,0.809,0.538,10,-0.11,null]],"MT":[[96778,68,0.044,0.09,28,1.9,null],[141568,68,0.059,0.079,18,2.92,null],[95816,68,0.059,0.123,19,4.24,null],[141562,68,0.088,0.107,9,2.57,null],[27847,68,0.118,0.092,3,3.46,null],[84405,68,0.118,0.135,2,2.27,null],[88952,68,0.132,0.158,22,2.43,null],[111771,68,0.132,0.108,15,2.19,null],[8460,68,0.147,0.082,29,2.81,null],[125905,68,0.162,0.185,6,1.78,null],[49136,68,0.162,0.151,7,2.98,null],[83162,68,0.162,0.258,26,1.18,null],[141518,68,0.176,0.231,6,1.27,null],[15396,68,0.176,0.121,11,1.39,null],[125926,68,0.191,0.224,11,1.07,null],[44306,68,0.191,0.226,25,1.72,null],[83575,68,0.191,0.187,23,2.46,null],[16995,68,0.206,0.166,28,2.23,null],[44510,68,0.206,0.301,12,2.37,null],[49227,68,0.221,0.272,29,1.96,null],[111422,68,0.221,0.177,13,2.17,null],[50210,68,0.235,0.198,24,0.97,null],[31953,68,0.235,0.294,16,1.53,null],[63293,68,0.25,0.263,5,1.92,null],[84096,68,0.25,0.15,2,2.29,null],[63713,68,0.25,0.111,30,1.73,null],[153134,68,0.265,0.346,3,0.85,null],[28216,68,0.279,0.225,8,1.83,null],[111673,68,0.279,0.284,14,2.02,null],[117856,68,0.294,0.239,18,1.83,null],[117625,68,0.309,0.314,19,1.24,null],[86942,68,0.338,0.319,9,2.91,null],[28587,68,0.338,0.257,16,1.06,null],[126023,68,0.397,0.376,10,0.46,null],[41895,68,0.397,0.316,12,1.39,null],[38222,68,0.397,0.303,27,0.99,null],[117764,68,0.426,0.552,20,-0.19,null],[16540,68,0.426,0.243,8,2.35,null],[63313,68,0.441,0.297,4,0.32,null],[96979,68,0.441,0.459,1,0.09,null],[60344,68,0.441,0.251,4,0.88,null],[95625,68,0.471,0.319,17,0.77,null],[96852,68,0.632,0.452,25,0.32,null]]},"hist_resumo":[{"ano":2024,"n_participantes":55,"media_geral":499.1,"media_cn":436.3,"media_ch":472.7,"media_lc":505.9,"media_mt":475.8,"media_red":588.1,"media_comp1":115.7,"media_comp2":135.1,"media_comp3":107.6,"media_comp4":124.3,"media_comp5":105.4},{"ano":2025,"n_participantes":79,"media_geral":483.5,"media_cn":472.5,"media_ch":477.9,"media_lc":507.1,"media_mt":468.5,"media_red":467.8,"media_comp1":95.0,"media_comp2":111.9,"media_comp3":90.6,"media_comp4":96.7,"media_comp5":73.6}],"hist_scope":{"primeiro_ano_com_escola":2024,"nota":"Antes de 2024 o INEP não expunha o código INEP nos microdados; portanto o histórico da escola começa em 2024."}}