{"T":[{"chave":"11041951","nome":"COOPERATIVA EDUCACIONAL DE VILHENA","uf":"RO","co_municipio":"1100304","municipio":"Vilhena","dependencia":4,"dependencia_nome":"Privada","n_participantes":40,"n_lc":40,"n_ch":40,"n_cn":39,"n_mt":39,"n_red":40,"media_geral":652.8,"media_red":801.0,"media_lc":595.2,"media_ch":584.7,"media_cn":581.8,"media_mt":690.8},{"chave":"11033215","nome":"CENTRO EDUCACIONAL ISOLINA RUTTMANN - SESI","uf":"RO","co_municipio":"1100304","municipio":"Vilhena","dependencia":4,"dependencia_nome":"Privada","n_participantes":64,"n_lc":58,"n_ch":58,"n_cn":58,"n_mt":58,"n_red":58,"media_geral":568.3,"media_red":675.9,"media_lc":544.1,"media_ch":528.3,"media_cn":518.9,"media_mt":574.2},{"chave":"11107804","nome":"IFRO - CAMPUS VILHENA","uf":"RO","co_municipio":"1100304","municipio":"Vilhena","dependencia":1,"dependencia_nome":"Federal","n_participantes":174,"n_lc":157,"n_ch":157,"n_cn":153,"n_mt":153,"n_red":157,"media_geral":549.4,"media_red":620.1,"media_lc":546.7,"media_ch":516.7,"media_cn":512.1,"media_mt":546.9},{"chave":"11033835","nome":"COLEGIO TIRADENTES DA POLICIA MILITAR - CTPM V","uf":"RO","co_municipio":"1100304","municipio":"Vilhena","dependencia":2,"dependencia_nome":"Estadual","n_participantes":118,"n_lc":100,"n_ch":100,"n_cn":93,"n_mt":93,"n_red":100,"media_geral":507.0,"media_red":549.8,"media_lc":511.9,"media_ch":488.9,"media_cn":483.1,"media_mt":482.9},{"chave":"11033797","nome":"EEEFM ALVARES DE AZEVEDO","uf":"RO","co_municipio":"1100304","municipio":"Vilhena","dependencia":2,"dependencia_nome":"Estadual","n_participantes":287,"n_lc":204,"n_ch":204,"n_cn":191,"n_mt":191,"n_red":204,"media_geral":504.9,"media_red":548.1,"media_lc":509.6,"media_ch":485.8,"media_cn":479.6,"media_mt":482.6},{"chave":"11033819","nome":"EEEM EM TEMPO INTEGRAL MARECHAL RONDON","uf":"RO","co_municipio":"1100304","municipio":"Vilhena","dependencia":2,"dependencia_nome":"Estadual","n_participantes":35,"n_lc":31,"n_ch":31,"n_cn":31,"n_mt":31,"n_red":31,"media_geral":499.9,"media_red":548.4,"media_lc":509.9,"media_ch":488.6,"media_cn":486.6,"media_mt":466.2},{"chave":"11106867","nome":"EEEFM SHIRLEI CERUTI","uf":"RO","co_municipio":"1100304","municipio":"Vilhena","dependencia":2,"dependencia_nome":"Estadual","n_participantes":208,"n_lc":139,"n_ch":139,"n_cn":125,"n_mt":125,"n_red":139,"media_geral":492.8,"media_red":550.4,"media_lc":494.9,"media_ch":465.1,"media_cn":476.1,"media_mt":459.1},{"chave":"11033649","nome":"EEEFM MARIA ARLETE TOLEDO","uf":"RO","co_municipio":"1100304","municipio":"Vilhena","dependencia":2,"dependencia_nome":"Estadual","n_participantes":349,"n_lc":173,"n_ch":173,"n_cn":149,"n_mt":149,"n_red":173,"media_geral":492.7,"media_red":518.7,"media_lc":498.0,"media_ch":467.9,"media_cn":473.0,"media_mt":465.0}],"PUB":[{"chave":"11107804","nome":"IFRO - CAMPUS VILHENA","uf":"RO","co_municipio":"1100304","municipio":"Vilhena","dependencia":1,"dependencia_nome":"Federal","n_participantes":174,"n_lc":157,"n_ch":157,"n_cn":153,"n_mt":153,"n_red":157,"media_geral":549.4,"media_red":620.1,"media_lc":546.7,"media_ch":516.7,"media_cn":512.1,"media_mt":546.9},{"chave":"11033835","nome":"COLEGIO TIRADENTES DA POLICIA MILITAR - CTPM V","uf":"RO","co_municipio":"1100304","municipio":"Vilhena","dependencia":2,"dependencia_nome":"Estadual","n_participantes":118,"n_lc":100,"n_ch":100,"n_cn":93,"n_mt":93,"n_red":100,"media_geral":507.0,"media_red":549.8,"media_lc":511.9,"media_ch":488.9,"media_cn":483.1,"media_mt":482.9},{"chave":"11033797","nome":"EEEFM ALVARES DE AZEVEDO","uf":"RO","co_municipio":"1100304","municipio":"Vilhena","dependencia":2,"dependencia_nome":"Estadual","n_participantes":287,"n_lc":204,"n_ch":204,"n_cn":191,"n_mt":191,"n_red":204,"media_geral":504.9,"media_red":548.1,"media_lc":509.6,"media_ch":485.8,"media_cn":479.6,"media_mt":482.6},{"chave":"11033819","nome":"EEEM EM TEMPO INTEGRAL MARECHAL RONDON","uf":"RO","co_municipio":"1100304","municipio":"Vilhena","dependencia":2,"dependencia_nome":"Estadual","n_participantes":35,"n_lc":31,"n_ch":31,"n_cn":31,"n_mt":31,"n_red":31,"media_geral":499.9,"media_red":548.4,"media_lc":509.9,"media_ch":488.6,"media_cn":486.6,"media_mt":466.2},{"chave":"11106867","nome":"EEEFM SHIRLEI CERUTI","uf":"RO","co_municipio":"1100304","municipio":"Vilhena","dependencia":2,"dependencia_nome":"Estadual","n_participantes":208,"n_lc":139,"n_ch":139,"n_cn":125,"n_mt":125,"n_red":139,"media_geral":492.8,"media_red":550.4,"media_lc":494.9,"media_ch":465.1,"media_cn":476.1,"media_mt":459.1},{"chave":"11033649","nome":"EEEFM MARIA ARLETE TOLEDO","uf":"RO","co_municipio":"1100304","municipio":"Vilhena","dependencia":2,"dependencia_nome":"Estadual","n_participantes":349,"n_lc":173,"n_ch":173,"n_cn":149,"n_mt":149,"n_red":173,"media_geral":492.7,"media_red":518.7,"media_lc":498.0,"media_ch":467.9,"media_cn":473.0,"media_mt":465.0}],"PRIV":[{"chave":"11041951","nome":"COOPERATIVA EDUCACIONAL DE VILHENA","uf":"RO","co_municipio":"1100304","municipio":"Vilhena","dependencia":4,"dependencia_nome":"Privada","n_participantes":40,"n_lc":40,"n_ch":40,"n_cn":39,"n_mt":39,"n_red":40,"media_geral":652.8,"media_red":801.0,"media_lc":595.2,"media_ch":584.7,"media_cn":581.8,"media_mt":690.8},{"chave":"11033215","nome":"CENTRO EDUCACIONAL ISOLINA RUTTMANN - SESI","uf":"RO","co_municipio":"1100304","municipio":"Vilhena","dependencia":4,"dependencia_nome":"Privada","n_participantes":64,"n_lc":58,"n_ch":58,"n_cn":58,"n_mt":58,"n_red":58,"media_geral":568.3,"media_red":675.9,"media_lc":544.1,"media_ch":528.3,"media_cn":518.9,"media_mt":574.2}]}