{"T":[{"chave":"15049809","nome":"EEEF PROF MANOEL JOAQUIM MONTEIRO SEDE","uf":"PA","co_municipio":"1504109","municipio":"Magalhães Barata","dependencia":2,"dependencia_nome":"Estadual","n_participantes":63,"media_geral":439.2,"media_red":450.8,"media_lc":459.8,"media_ch":436.4,"media_cn":434.0,"media_mt":421.1}],"PUB":[{"chave":"15049809","nome":"EEEF PROF MANOEL JOAQUIM MONTEIRO SEDE","uf":"PA","co_municipio":"1504109","municipio":"Magalhães Barata","dependencia":2,"dependencia_nome":"Estadual","n_participantes":63,"media_geral":439.2,"media_red":450.8,"media_lc":459.8,"media_ch":436.4,"media_cn":434.0,"media_mt":421.1}],"PRIV":[]}