{"T":[{"chave":"29225060","nome":"COLEGIO ESTADUAL ANTONIO CARLOS MAGALHAES","uf":"BA","co_municipio":"2914307","municipio":"Iramaia","dependencia":2,"dependencia_nome":"Estadual","n_participantes":36,"media_geral":453.7,"media_red":453.3,"media_lc":471.2,"media_ch":450.7,"media_cn":452.5,"media_mt":432.0}],"PUB":[{"chave":"29225060","nome":"COLEGIO ESTADUAL ANTONIO CARLOS MAGALHAES","uf":"BA","co_municipio":"2914307","municipio":"Iramaia","dependencia":2,"dependencia_nome":"Estadual","n_participantes":36,"media_geral":453.7,"media_red":453.3,"media_lc":471.2,"media_ch":450.7,"media_cn":452.5,"media_mt":432.0}],"PRIV":[]}