{"T":[{"chave":"41028945","nome":"INSTITUTO NOSSA SENHORA AUXILIADORA","uf":"PR","co_municipio":"4103701","municipio":"Cambé","dependencia":4,"dependencia_nome":"Privada","n_participantes":57,"n_lc":49,"n_ch":49,"n_cn":48,"n_mt":48,"n_red":49,"media_geral":576.3,"media_red":642.4,"media_lc":579.8,"media_ch":563.8,"media_cn":524.4,"media_mt":575.8},{"chave":"41028457","nome":"ATTILIO CODATO C E EF M PROFIS","uf":"PR","co_municipio":"4103701","municipio":"Cambé","dependencia":2,"dependencia_nome":"Estadual","n_participantes":100,"n_lc":90,"n_ch":90,"n_cn":83,"n_mt":83,"n_red":90,"media_geral":549.3,"media_red":611.3,"media_lc":551.7,"media_ch":539.0,"media_cn":501.7,"media_mt":540.6},{"chave":"41028430","nome":"ANTONIO RAMINELLI C E C M EF M PROFIS","uf":"PR","co_municipio":"4103701","municipio":"Cambé","dependencia":2,"dependencia_nome":"Estadual","n_participantes":47,"n_lc":39,"n_ch":39,"n_cn":36,"n_mt":36,"n_red":39,"media_geral":544.1,"media_red":599.0,"media_lc":555.8,"media_ch":514.9,"media_cn":499.1,"media_mt":537.3},{"chave":"41028732","nome":"HELENA KOLODY C E PROF EF M","uf":"PR","co_municipio":"4103701","municipio":"Cambé","dependencia":2,"dependencia_nome":"Estadual","n_participantes":68,"n_lc":54,"n_ch":54,"n_cn":50,"n_mt":50,"n_red":54,"media_geral":532.2,"media_red":553.7,"media_lc":545.5,"media_ch":521.6,"media_cn":496.8,"media_mt":525.2},{"chave":"41028570","nome":"ERICO VERISSIMO C E C M EF M PROFIS","uf":"PR","co_municipio":"4103701","municipio":"Cambé","dependencia":2,"dependencia_nome":"Estadual","n_participantes":64,"n_lc":48,"n_ch":48,"n_cn":43,"n_mt":43,"n_red":48,"media_geral":529.5,"media_red":558.8,"media_lc":539.9,"media_ch":526.8,"media_cn":501.5,"media_mt":506.1},{"chave":"41028406","nome":"ANDREA NUZZI C E MAESTRO EF M PROFIS","uf":"PR","co_municipio":"4103701","municipio":"Cambé","dependencia":2,"dependencia_nome":"Estadual","n_participantes":99,"n_lc":85,"n_ch":85,"n_cn":81,"n_mt":81,"n_red":85,"media_geral":485.9,"media_red":471.1,"media_lc":513.3,"media_ch":485.1,"media_cn":465.5,"media_mt":478.2}],"PUB":[{"chave":"41028457","nome":"ATTILIO CODATO C E EF M PROFIS","uf":"PR","co_municipio":"4103701","municipio":"Cambé","dependencia":2,"dependencia_nome":"Estadual","n_participantes":100,"n_lc":90,"n_ch":90,"n_cn":83,"n_mt":83,"n_red":90,"media_geral":549.3,"media_red":611.3,"media_lc":551.7,"media_ch":539.0,"media_cn":501.7,"media_mt":540.6},{"chave":"41028430","nome":"ANTONIO RAMINELLI C E C M EF M PROFIS","uf":"PR","co_municipio":"4103701","municipio":"Cambé","dependencia":2,"dependencia_nome":"Estadual","n_participantes":47,"n_lc":39,"n_ch":39,"n_cn":36,"n_mt":36,"n_red":39,"media_geral":544.1,"media_red":599.0,"media_lc":555.8,"media_ch":514.9,"media_cn":499.1,"media_mt":537.3},{"chave":"41028732","nome":"HELENA KOLODY C E PROF EF M","uf":"PR","co_municipio":"4103701","municipio":"Cambé","dependencia":2,"dependencia_nome":"Estadual","n_participantes":68,"n_lc":54,"n_ch":54,"n_cn":50,"n_mt":50,"n_red":54,"media_geral":532.2,"media_red":553.7,"media_lc":545.5,"media_ch":521.6,"media_cn":496.8,"media_mt":525.2},{"chave":"41028570","nome":"ERICO VERISSIMO C E C M EF M PROFIS","uf":"PR","co_municipio":"4103701","municipio":"Cambé","dependencia":2,"dependencia_nome":"Estadual","n_participantes":64,"n_lc":48,"n_ch":48,"n_cn":43,"n_mt":43,"n_red":48,"media_geral":529.5,"media_red":558.8,"media_lc":539.9,"media_ch":526.8,"media_cn":501.5,"media_mt":506.1},{"chave":"41028406","nome":"ANDREA NUZZI C E MAESTRO EF M PROFIS","uf":"PR","co_municipio":"4103701","municipio":"Cambé","dependencia":2,"dependencia_nome":"Estadual","n_participantes":99,"n_lc":85,"n_ch":85,"n_cn":81,"n_mt":81,"n_red":85,"media_geral":485.9,"media_red":471.1,"media_lc":513.3,"media_ch":485.1,"media_cn":465.5,"media_mt":478.2}],"PRIV":[{"chave":"41028945","nome":"INSTITUTO NOSSA SENHORA AUXILIADORA","uf":"PR","co_municipio":"4103701","municipio":"Cambé","dependencia":4,"dependencia_nome":"Privada","n_participantes":57,"n_lc":49,"n_ch":49,"n_cn":48,"n_mt":48,"n_red":49,"media_geral":576.3,"media_red":642.4,"media_lc":579.8,"media_ch":563.8,"media_cn":524.4,"media_mt":575.8}]}