{"T":[{"chave":"52039625","nome":"COLEGIO ESTADUAL ALFREDO NASSER","uf":"GO","co_municipio":"5221197","municipio":"Terezópolis de Goiás","dependencia":2,"dependencia_nome":"Estadual","n_participantes":70,"media_geral":503.9,"media_red":567.0,"media_lc":497.8,"media_ch":468.4,"media_cn":468.4,"media_mt":487.8}],"PUB":[{"chave":"52039625","nome":"COLEGIO ESTADUAL ALFREDO NASSER","uf":"GO","co_municipio":"5221197","municipio":"Terezópolis de Goiás","dependencia":2,"dependencia_nome":"Estadual","n_participantes":70,"media_geral":503.9,"media_red":567.0,"media_lc":497.8,"media_ch":468.4,"media_cn":468.4,"media_mt":487.8}],"PRIV":[]}