[{"chave":"35910533","nome":"ORLANDO MAURICIO ZAMBOTTO","dependencia":2,"n_participantes":99,"n_lc":41,"n_mt":41,"media_geral":525.5,"rotulo":"ORLANDO MAURICIO ZAMBOTTO · Estadual"},{"chave":"35919305","nome":"DUILIO MAZIERO","dependencia":2,"n_participantes":78,"n_lc":22,"n_mt":18,"media_geral":529.2,"rotulo":"DUILIO MAZIERO · Estadual"},{"chave":"35019860","nome":"JERONIMO DE CAMARGO","dependencia":2,"n_participantes":70,"n_lc":46,"n_mt":45,"media_geral":512.5,"rotulo":"JERONIMO DE CAMARGO · Estadual"},{"chave":"35901222","nome":"ZULMIRO ALVES DE SIQUEIRA","dependencia":2,"n_participantes":50,"n_lc":15,"n_mt":14,"media_geral":512.7,"rotulo":"ZULMIRO ALVES DE SIQUEIRA · Estadual"},{"chave":"35165438","nome":"PILAR BONAS ASSOCIACAO DE ENSINO","dependencia":4,"n_participantes":13,"n_lc":8,"n_mt":7,"media_geral":637.1,"rotulo":"PILAR BONAS ASSOCIACAO DE ENSINO · Privada"},{"chave":"60020620","nome":null,"dependencia":4,"n_participantes":6,"n_lc":6,"n_mt":6,"media_geral":560.6,"rotulo":"Escola INEP 60020620 · Privada"}]