[{"chave":"42089263","nome":"EEB FREI MENANDRO KAMPS","dependencia":2,"n_participantes":63,"media_geral":457.5,"rotulo":"EEB FREI MENANDRO KAMPS · Estadual"},{"chave":"42089255","nome":"EEB COLOMBO MACHADO SALLES","dependencia":2,"n_participantes":34,"media_geral":495.0,"rotulo":"EEB COLOMBO MACHADO SALLES · Estadual"},{"chave":"60025468","nome":null,"dependencia":2,"n_participantes":7,"media_geral":null,"rotulo":"Escola INEP 60025468 · Estadual"},{"chave":"60025775","nome":null,"dependencia":2,"n_participantes":2,"media_geral":414.2,"rotulo":"Escola INEP 60025775 · Estadual"}]